CHANGES.rst
CONTRIBUTORS.txt
LICENSE
MANIFEST.in
README.rst
setup.py
lshash/__init__.py
lshash/lshash.py
lshash/storage.py
lshash.egg-info/PKG-INFO
lshash.egg-info/SOURCES.txt
lshash.egg-info/dependency_links.txt
lshash.egg-info/top_level.txt