Metadata-Version: 1.1
Name: lshash
Version: 0.0.4dev
Summary: A fast Python implementation of locality sensitive hashing with persistance support.
Home-page: UNKNOWN
Author: Kay Zhu
Author-email: me@kayzhu.com
License: Copyright 2012 Kay Zhu (a.k.a He Zhu)
